my_toyota_package/__init__.py
my_toyota_package/decision_tree.py
my_toyota_package/data/ToyotaCorolla.csv
my_toyota_package-0.7.dist-info/METADATA
my_toyota_package-0.7.dist-info/WHEEL
my_toyota_package-0.7.dist-info/entry_points.txt
my_toyota_package-0.7.dist-info/top_level.txt
my_toyota_package-0.7.dist-info/RECORD
