Metadata-Version: 2.1
Name: my_toyota_package
Version: 0.7
Summary: A machine learning package for optimizing and training decision trees on Toyota Corolla dataset
Home-page: https://github.com/yourusername/my_toyota_package
Author: Your Name
Author-email: your.email@example.com
Classifier: Programming Language :: Python :: 3
Classifier: License :: OSI Approved :: MIT License
Classifier: Operating System :: OS Independent
Requires-Python: >=3.6
Requires-Dist: pandas
Requires-Dist: scikit-learn
